sqlist
tests
