Metadata-Version: 1.1
Name: sqlist
Version: 0.2.1b
Summary: List-like wrapper for SQLite
Home-page: https://github.com/valericus/sqlist
Author: Valery Ryaboshapko
Author-email: valera@creator.su
License: MIT
Platform: UNKNOWN
Classifier: Development Status :: 4 - Beta
Classifier: License :: OSI Approved :: MIT License
Classifier: Operating System :: OS Independent
Classifier: Programming Language :: Python :: 2
Classifier: Programming Language :: Python :: 2.6
Classifier: Programming Language :: Python :: 2.7
Classifier: Programming Language :: Python :: 3
Classifier: Programming Language :: Python :: 3.3
Classifier: Programming Language :: Python :: 3.4
Classifier: Programming Language :: Python :: 3.5
